MVPR/MVPR.py
MVPR/__init__.py
MVPR-1.32.dist-info/LICENSE.txt
MVPR-1.32.dist-info/METADATA
MVPR-1.32.dist-info/WHEEL
MVPR-1.32.dist-info/top_level.txt
MVPR-1.32.dist-info/RECORD
