Metadata-Version: 2.1
Name: MVPR
Version: 1.32
Summary: Multi-variable polynomial regression for curve fitting.
Home-page: https://github.com/Joel-H-dot/MVPR
Author: Joel Hampton
Author-email: joelelihampton@outlook.com
License: MIT
Download-URL: https://github.com/Joel-H-dot/MVPR/archive/refs/tags/1.1.tar.gz
Keywords: Machine Learning,Regression,polynomial
Platform: UNKNOWN
Classifier: Development Status :: 4 - Beta
Classifier: Intended Audience :: Science/Research 
Classifier: License :: OSI Approved :: MIT License
Classifier: Programming Language :: Python :: 3
License-File: LICENSE.txt
Requires-Dist: numpy
Requires-Dist: sklearn
Requires-Dist: scipy
